LICENSE
README.md
pyproject.toml
setup.cfg
setup.py
src/reg/__init__.py
src/reg/regression.py
src/regression_transform_helpers_nicktheprick.egg-info/PKG-INFO
src/regression_transform_helpers_nicktheprick.egg-info/SOURCES.txt
src/regression_transform_helpers_nicktheprick.egg-info/dependency_links.txt
src/regression_transform_helpers_nicktheprick.egg-info/requires.txt
src/regression_transform_helpers_nicktheprick.egg-info/top_level.txt