Metadata-Version: 2.1
Name: regression-transform-helpers-nicktheprick
Version: 0.0.1
Summary: Helpers for certain regression
Home-page: https://github.com/Nick-Yazdani/regression-transform-helpers
Author: Nick Yazdani
Author-email: nnyazdani92@gmail.com
License: MIT
Keywords: regression transformers helpers
Platform: UNKNOWN
Classifier: Programming Language :: Python :: 3
Classifier: License :: OSI Approved :: MIT License
Classifier: Operating System :: OS Independent
Requires-Python: >=3.6
License-File: LICENSE
